folio/__init__.py
folio/config.py
folio/graph.py
folio/logger.py
folio/models.py
folio_python-0.2.0.dist-info/METADATA
folio_python-0.2.0.dist-info/WHEEL
folio_python-0.2.0.dist-info/licenses/LICENSE
folio_python-0.2.0.dist-info/RECORD
