Metadata-Version: 2.4
Name: folio-python
Version: 0.2.0
Summary: Python library for FOLIO, the Federated Open Legal Information Ontology
Project-URL: Homepage, https://openlegalstandard.org/
Project-URL: Repository, https://github.com/alea-institute/folio-python
Project-URL: Documentation, https://openlegalstandard.org/docs/
Author-email: ALEA Institute <hello@aleainstitute.ai>
License-Expression: MIT
License-File: LICENSE
Keywords: folio,information,legal,open,standard
Classifier: Development Status :: 3 - Alpha
Classifier: Intended Audience :: Developers
Classifier: Intended Audience :: Legal Industry
Classifier: Intended Audience :: Science/Research
Classifier: License :: OSI Approved :: MIT License
Classifier: Operating System :: OS Independent
Classifier: Programming Language :: Python
Classifier: Programming Language :: Python :: 3
Classifier: Programming Language :: Python :: 3.10
Classifier: Programming Language :: Python :: 3.11
Classifier: Programming Language :: Python :: 3.12
Classifier: Topic :: Scientific/Engineering :: Artificial Intelligence
Classifier: Topic :: Scientific/Engineering :: Information Analysis
Classifier: Topic :: Software Development :: Libraries :: Python Modules
Classifier: Topic :: Text Processing :: Markup :: XML
Classifier: Topic :: Utilities
Requires-Python: <4.0.0,>=3.10
Requires-Dist: httpx>=0.27.2
Requires-Dist: lxml>=5.2.2
Requires-Dist: pydantic>=2.8.2
Provides-Extra: search
Requires-Dist: alea-llm-client>=0.1.1; extra == 'search'
Requires-Dist: marisa-trie<2,>=1.2.0; extra == 'search'
Requires-Dist: rapidfuzz<4,>=3.10.0; extra == 'search'
